dbt_coverage/__init__.py
dbt_coverage-0.4.1.dist-info/LICENSE.md
dbt_coverage-0.4.1.dist-info/METADATA
dbt_coverage-0.4.1.dist-info/WHEEL
dbt_coverage-0.4.1.dist-info/entry_points.txt
dbt_coverage-0.4.1.dist-info/RECORD
