Metadata-Version: 2.3
Name: dbt-coverage
Version: 0.4.1
Summary: One-stop-shop for docs and test coverage of dbt projects
License: MIT
Author: Andrej Švec
Author-email: asvec@slido.com
Requires-Python: >=3.7,<4.0
Classifier: Development Status :: 4 - Beta
Classifier: Intended Audience :: Developers
Classifier: License :: OSI Approved :: MIT License
Classifier: Operating System :: OS Independent
Classifier: Programming Language :: Python :: 3
Classifier: Programming Language :: Python :: 3.7
Classifier: Programming Language :: Python :: 3.8
Classifier: Programming Language :: Python :: 3.9
Classifier: Programming Language :: Python :: 3.10
Classifier: Programming Language :: Python :: 3.11
Classifier: Programming Language :: Python :: 3.12
Classifier: Programming Language :: Python :: 3.13
Classifier: Programming Language :: Python :: 3 :: Only
Classifier: Programming Language :: Python :: 3.6
Requires-Dist: typer (>=0.4,<1)
Project-URL: Documentation, https://github.com/slidoapp/dbt-coverage
Project-URL: Homepage, https://github.com/slidoapp/dbt-coverage
Project-URL: Repository, https://github.com/slidoapp/dbt-coverage
